odoo/addons/mrp_workcenter_dashboard/README.rst
odoo/addons/mrp_workcenter_dashboard/__init__.py
odoo/addons/mrp_workcenter_dashboard/__manifest__.py
odoo/addons/mrp_workcenter_dashboard/i18n/es.po
odoo/addons/mrp_workcenter_dashboard/i18n/mrp_workcenter_dashboard.pot
odoo/addons/mrp_workcenter_dashboard/readme/CONTRIBUTORS.rst
odoo/addons/mrp_workcenter_dashboard/readme/DESCRIPTION.rst
odoo/addons/mrp_workcenter_dashboard/static/description/icon.png
odoo/addons/mrp_workcenter_dashboard/static/description/index.html
odoo/addons/mrp_workcenter_dashboard/views/mrp_workcenter_views.xml
odoo_addon_mrp_workcenter_dashboard-16.0.1.0.0.2.dist-info/METADATA
odoo_addon_mrp_workcenter_dashboard-16.0.1.0.0.2.dist-info/WHEEL
odoo_addon_mrp_workcenter_dashboard-16.0.1.0.0.2.dist-info/top_level.txt
odoo_addon_mrp_workcenter_dashboard-16.0.1.0.0.2.dist-info/RECORD
